rivr_peewee/__init__.py
rivr_peewee/database.py
rivr_peewee/views.py
rivr_peewee/tests/__init__.py
rivr_peewee/tests/test_database.py
rivr_peewee-0.2.1.dist-info/DESCRIPTION.rst
rivr_peewee-0.2.1.dist-info/METADATA
rivr_peewee-0.2.1.dist-info/RECORD
rivr_peewee-0.2.1.dist-info/WHEEL
rivr_peewee-0.2.1.dist-info/metadata.json
rivr_peewee-0.2.1.dist-info/top_level.txt
