Metadata-Version: 2.0
Name: rivr-peewee
Version: 0.2.1
Summary: rivr integration for the peewee database ORM.
Home-page: https://github.com/rivrproject/rivr-peewee
Author: Kyle Fuller
Author-email: kyle@fuller.li
License: BSD
Platform: UNKNOWN
Requires-Dist: rivr
Requires-Dist: peewee
